orthority/__init__.py
orthority/camera.py
orthority/cli.py
orthority/common.py
orthority/enums.py
orthority/errors.py
orthority/exif.py
orthority/factory.py
orthority/fit.py
orthority/ortho.py
orthority/pan_sharp.py
orthority/param_io.py
orthority/py.typed
orthority/version.py
orthority-0.6.1.dist-info/licenses/LICENSE
orthority-0.6.1.dist-info/METADATA
orthority-0.6.1.dist-info/WHEEL
orthority-0.6.1.dist-info/entry_points.txt
orthority-0.6.1.dist-info/top_level.txt
orthority-0.6.1.dist-info/RECORD
