Metadata-Version: 2.4
Name: orthority
Version: 0.6.1
Summary: Orthorectification of drone, aerial and satellite imagery.
Author: Leftfield Geospatial
License: AGPL-3.0-or-later
Project-URL: Homepage, https://github.com/leftfield-geospatial/orthority
Project-URL: Documentation, https://orthority.readthedocs.org
Project-URL: Source, https://github.com/leftfield-geospatial/orthority
Project-URL: Changelog, https://github.com/leftfield-geospatial/orthority/releases
Project-URL: Issues, https://github.com/leftfield-geospatial/orthority/issues
Keywords: orthorectify,orthorectification,georeference,uav,drone,aerial,satellite,exif,xmp,image,rpc
Classifier: Programming Language :: Python :: 3
Classifier: License :: OSI Approved :: GNU Affero General Public License v3 or later (AGPLv3+)
Classifier: Operating System :: OS Independent
Requires-Python: >=3.9
License-File: LICENSE
Requires-Dist: rasterio>=1.3.6
Requires-Dist: opencv-python-headless>=4.8
Requires-Dist: pyyaml>=5
Requires-Dist: click>=8
Requires-Dist: tqdm>=4
Requires-Dist: fsspec>=2023.12
Provides-Extra: http
Requires-Dist: requests; extra == "http"
Requires-Dist: aiohttp; extra == "http"
Provides-Extra: tests
Requires-Dist: pytest; extra == "tests"
Requires-Dist: requests; extra == "tests"
Requires-Dist: aiohttp; extra == "tests"
Provides-Extra: docs
Requires-Dist: sphinx; extra == "docs"
Requires-Dist: furo; extra == "docs"
Requires-Dist: sphinx-click; extra == "docs"
Requires-Dist: sphinx-argparse; extra == "docs"
Requires-Dist: sphinx-copybutton; extra == "docs"
Dynamic: license-file
